edc_form_describer/__init__.py
edc_form_describer/apps.py
edc_form_describer/form_describer.py
edc_form_describer/forms_reference.py
edc_form_describer/make_forms_reference.py
edc_form_describer/markdown_writer.py
edc_form_describer/models.py
edc_form_describer/urls.py
edc_form_describer/management/__init__.py
edc_form_describer/management/commands/__init__.py
edc_form_describer/management/commands/make_forms_reference.py
edc_form_describer/migrations/__init__.py
edc_form_describer/tests/__init__.py
edc_form_describer/tests/admin.py
edc_form_describer/tests/forms.py
edc_form_describer/tests/models.py
edc_form_describer/tests/urls.py
edc_form_describer/tests/visit_schedule.py
edc_form_describer/tests/tests/__init__.py
edc_form_describer/tests/tests/tests.py
edc_form_describer-1.0.2.dist-info/licenses/LICENSE
edc_form_describer-1.0.2.dist-info/METADATA
edc_form_describer-1.0.2.dist-info/WHEEL
edc_form_describer-1.0.2.dist-info/top_level.txt
edc_form_describer-1.0.2.dist-info/RECORD
